flake8_errmsg/__init__.py
flake8_errmsg/__main__.py
flake8_errmsg/py.typed
flake8_errmsg-0.6.0.dist-info/METADATA
flake8_errmsg-0.6.0.dist-info/WHEEL
flake8_errmsg-0.6.0.dist-info/entry_points.txt
flake8_errmsg-0.6.0.dist-info/licenses/LICENSE
flake8_errmsg-0.6.0.dist-info/RECORD
