Metadata-Version: 2.4
Name: flake8_errmsg
Version: 0.6.0
Summary: Flake8 checker for raw literals inside raises.
Project-URL: homepage, https://github.com/henryiii/flake8-errmsg
Author-email: Henry Schreiner <henryschreineriii@gmail.com>
License-File: LICENSE
Classifier: Development Status :: 5 - Production/Stable
Classifier: Framework :: Flake8
Classifier: Intended Audience :: Developers
Classifier: License :: OSI Approved :: Apache Software License
Classifier: Operating System :: OS Independent
Classifier: Programming Language :: Python
Classifier: Programming Language :: Python :: 3
Classifier: Programming Language :: Python :: 3.10
Classifier: Programming Language :: Python :: 3.11
Classifier: Programming Language :: Python :: 3.12
Classifier: Programming Language :: Python :: 3.13
Classifier: Programming Language :: Python :: 3.14
Classifier: Topic :: Software Development :: Libraries :: Python Modules
Classifier: Topic :: Software Development :: Quality Assurance
Classifier: Typing :: Typed
Requires-Python: >=3.10
Provides-Extra: dev
Requires-Dist: flake8; extra == 'dev'
Requires-Dist: pytest>=7; extra == 'dev'
Provides-Extra: test
Requires-Dist: pytest>=7; extra == 'test'
